recur/__init__.py
recur/abc.py
recur/tree.py
recur/trees.py
recursive_abc-0.2.0.dist-info/LICENSE
recursive_abc-0.2.0.dist-info/METADATA
recursive_abc-0.2.0.dist-info/WHEEL
recursive_abc-0.2.0.dist-info/top_level.txt
recursive_abc-0.2.0.dist-info/RECORD
