Metadata-Version: 2.1
Name: recursive-abc
Version: 0.2.0
Summary: A package to simplify the creation and manipulation of recursive data structures.
Home-page: https://github.com/sdeslauriers/recur
Author: Samuel Deslauriers-Gauthier
Author-email: sam.deslauriers@gmail.com
License: UNKNOWN
Keywords: recursive data structure tree graph
Platform: UNKNOWN
Classifier: License :: OSI Approved :: GNU General Public License v3 (GPLv3)
Classifier: Development Status :: 3 - Alpha
Classifier: Intended Audience :: Developers
Classifier: Programming Language :: Python :: 3.6
